README.md
setup.py
ctpbee_converter/__init__.py
ctpbee_converter/converter.py
ctpbee_converter/helper.py
ctpbee_converter.egg-info/PKG-INFO
ctpbee_converter.egg-info/SOURCES.txt
ctpbee_converter.egg-info/dependency_links.txt
ctpbee_converter.egg-info/requires.txt
ctpbee_converter.egg-info/top_level.txt
fancy/__init__.py
fancy/app.py
fancy/ext.py
fancy/strategy/__init__.py
fancy/strategy/easy_demo_str.py